SVDC/SVDC.py
SVDC/SVDC_CMA.py
SVDC/__init__.py
SVDClassifier-0.1.1.dist-info/LICENSE.md
SVDClassifier-0.1.1.dist-info/METADATA
SVDClassifier-0.1.1.dist-info/WHEEL
SVDClassifier-0.1.1.dist-info/top_level.txt
SVDClassifier-0.1.1.dist-info/RECORD
