Metadata-Version: 2.1
Name: SVDClassifier
Version: 0.1.1
Summary: The SVD Classifier Package
Home-page: https://github.com/ConnAALL/SVDC
Author: Jay Nash
Author-email: Jay Nash <jnash1@conncoll.edu>
Project-URL: Homepage, https://github.com/ConnAALL/SVDC/
Project-URL: Issues, https://github.com/ConnAALL/SVDC/issues
Classifier: Programming Language :: Python :: 3
Classifier: License :: OSI Approved :: MIT License
Classifier: Operating System :: OS Independent
Requires-Python: >=3.6
License-File: LICENSE.md
